lilliepy/__init__.py
lilliepy-17.0.1.dist-info/METADATA
lilliepy-17.0.1.dist-info/WHEEL
lilliepy-17.0.1.dist-info/top_level.txt
lilliepy-17.0.1.dist-info/RECORD
