Metadata-Version: 2.4
Name: lilliepy
Version: 17.0.1
Summary: A Bundle of Pkgs for Lilliepy
Home-page: https://github.com/websitedeb/lilliepy
Author: sarthak ghoshal
Author-email: sarthak22.ghoshal@example.com
Classifier: Programming Language :: Python :: 3
Classifier: License :: OSI Approved :: MIT License
Classifier: Operating System :: OS Independent
Requires-Python: >=3.7
Requires-Dist: reactpy
Requires-Dist: reactpy-router
Requires-Dist: reactpy-utils
Requires-Dist: reactpy-forms
Requires-Dist: reactpy-table
Requires-Dist: reactpy-select
Requires-Dist: reactpy-apexcharts
Requires-Dist: lilliepy-dir-router
Requires-Dist: lilliepy-bling
Requires-Dist: lilliepy-head
Requires-Dist: lilliepy-statics
Requires-Dist: lilliepy-query
Requires-Dist: lilliepy-state
Requires-Dist: lilliepy-import
Requires-Dist: lilliepy-socket
Requires-Dist: lilliepy-build
Requires-Dist: lilliepy-protect
Requires-Dist: lillie-start
Requires-Dist: pytailwindcss
Requires-Dist: flask_sock
Requires-Dist: markdown
Requires-Dist: hquery
Requires-Dist: lilliepy-rebound
Requires-Dist: lilliepy-tags
Dynamic: author
Dynamic: author-email
Dynamic: classifier
Dynamic: description
Dynamic: description-content-type
Dynamic: home-page
Dynamic: requires-dist
Dynamic: requires-python
Dynamic: summary
